scss/__init__.py
scss/__main__.py
scss/ast.py
scss/calculator.py
scss/compiler.py
scss/config.py
scss/cssdefs.py
scss/errors.py
scss/legacy.py
scss/less2scss.py
scss/namespace.py
scss/rule.py
scss/scss_meta.py
scss/selector.py
scss/setup.py
scss/source.py
scss/tool.py
scss/types.py
scss/util.py
scss/extension/__init__.py
scss/extension/api.py
scss/extension/bootstrap.py
scss/extension/core.py
scss/extension/extra.py
scss/extension/fonts.py
scss/extension/compass/__init__.py
scss/extension/compass/gradients.py
scss/extension/compass/helpers.py
scss/extension/compass/images.py
scss/extension/compass/layouts.py
scss/extension/compass/sprites.py
scss/grammar/__init__.py
scss/grammar/expression.py
scss/grammar/scanner.py
scss/src/build.py
scss/tests/__init__.py
scss/tests/test_cli.py
scss/tests/test_expression.py
scss/tests/test_interactive.py
scss/tests/test_misc.py
scss/tests/test_types.py
scss/tests/util.py
scss/tests/extension/test_core.py
scss/tests/extension/test_extra.py
scss/tests/extension/compass/test_gradients.py
scss/tests/extension/compass/test_helpers.py
scss/tests/extension/compass/test_images.py
scss/tests/files/from-sassc/copy-tests-from-sassc.py
scss/tests/from_ruby/__init__.py
scss/tests/from_ruby/_test_scss.py
scss/tests/from_ruby/test_extend.py
mrowrpurr_pyscss-1.4.1.dist-info/METADATA
mrowrpurr_pyscss-1.4.1.dist-info/WHEEL
mrowrpurr_pyscss-1.4.1.dist-info/entry_points.txt
mrowrpurr_pyscss-1.4.1.dist-info/licenses/LICENSE
mrowrpurr_pyscss-1.4.1.dist-info/RECORD
