Metadata-Version: 2.4
Name: mrowrpurr-pyscss
Version: 1.4.1
Summary: pyScss, a Scss compiler for Python (Fork with Python 3.13+ support)
Project-URL: Homepage, https://github.com/mrowrpurr/pyScss
Project-URL: Original, https://github.com/Kronuz/pyScss
Project-URL: Repository, https://github.com/mrowrpurr/pyScss
Author-email: "German M. Bravo (Kronuz)" <german.mb@gmail.com>, mrowrpurr <mrowr.purr@gmail.com>
License-Expression: MIT
License-File: LICENSE
Keywords: css,less,oocss,precompiler,sass,scss,xcss
Classifier: Development Status :: 5 - Production/Stable
Classifier: Intended Audience :: Developers
Classifier: License :: OSI Approved :: MIT License
Classifier: Operating System :: OS Independent
Classifier: Programming Language :: Python
Classifier: Programming Language :: Python :: 3
Classifier: Programming Language :: Python :: 3.9
Classifier: Programming Language :: Python :: 3.10
Classifier: Programming Language :: Python :: 3.11
Classifier: Programming Language :: Python :: 3.12
Classifier: Programming Language :: Python :: 3.13
Classifier: Programming Language :: Python :: 3.14
Classifier: Topic :: Software Development :: Code Generators
Classifier: Topic :: Software Development :: Libraries :: Python Modules
Classifier: Topic :: Text Processing :: Markup
Requires-Python: >=3.9
Requires-Dist: six
